supervisor/__init__.py
supervisor/command_line.py
supervisor/convenience.py
supervisor/predictor.py
supervisor/utils.py
audio_cat-0.0.1.dist-info/LICENSE
audio_cat-0.0.1.dist-info/METADATA
audio_cat-0.0.1.dist-info/WHEEL
audio_cat-0.0.1.dist-info/entry_points.txt
audio_cat-0.0.1.dist-info/top_level.txt
audio_cat-0.0.1.dist-info/RECORD
